gaussquality/__init__.py
gaussquality/gaussquality_calc.py
gaussquality/gaussquality_fitting.py
gaussquality/gaussquality_gui.py
gaussquality/gaussquality_io.py
gaussquality/gaussquality_visuals.py
gaussquality-0.0.2.dist-info/LICENSE
gaussquality-0.0.2.dist-info/METADATA
gaussquality-0.0.2.dist-info/WHEEL
gaussquality-0.0.2.dist-info/top_level.txt
gaussquality-0.0.2.dist-info/RECORD
