Metadata-Version: 2.1
Name: gaussquality
Version: 0.0.2
Summary: Image quality assessment with Gaussian Mixture Models
Home-page: https://github.com/elainehoml/GaussQuality
Author: Elaine Ho
Author-email: mselaineho@gmail.com
License: UNKNOWN
Project-URL: Bug Tracker, https://github.com/elainehoml/GaussQuality/issues
Platform: UNKNOWN
Classifier: Programming Language :: Python :: 3
Classifier: License :: OSI Approved :: GNU General Public License v3 (GPLv3)
Classifier: Operating System :: OS Independent
License-File: LICENSE
Requires-Dist: gaussquality
Requires-Dist: numpy
Requires-Dist: scipy
Requires-Dist: pandas
Requires-Dist: matplotlib (==3.4.2)
Requires-Dist: tk
Requires-Dist: ttkthemes
Requires-Dist: scikit-image
Requires-Dist: scikit-learn
Requires-Dist: pytest
